pyzelda/__init__.py
pyzelda/zelda.py
pyzelda/ztools.py
pyzelda/instruments/CLASSIC.ini
pyzelda/instruments/HiCAT.ini
pyzelda/instruments/MISTI.ini
pyzelda/instruments/MITHIC-SCI.ini
pyzelda/instruments/MITHIC.ini
pyzelda/instruments/NEAR.ini
pyzelda/instruments/SPEED.ini
pyzelda/instruments/SPHERE-IFS.ini
pyzelda/instruments/SPHERE-IRDIS.ini
pyzelda/instruments/SPHERE-SAXO.ini
pyzelda/utils/__init__.py
pyzelda/utils/aperture.py
pyzelda/utils/circle_fit.py
pyzelda/utils/imutils.py
pyzelda/utils/mft.py
pyzelda/utils/prof.py
pyzelda/utils/zernike.py
pyzelda-1.3.dist-info/LICENSE
pyzelda-1.3.dist-info/METADATA
pyzelda-1.3.dist-info/WHEEL
pyzelda-1.3.dist-info/top_level.txt
pyzelda-1.3.dist-info/RECORD
