Metadata-Version: 2.1
Name: pyzelda
Version: 1.3
Summary: Zernike wavefront sensor analysis and simulation tools
Home-page: https://github.com/avigan/pyZELDA
Author: Arthur Vigan & Mamadou N'Diaye
Author-email: arthur.vigan@lam.fr, mamadou.ndiaye@oca.eu
License: MIT
Keywords: zernike wavefront sensor zelda
Classifier: Development Status :: 5 - Production/Stable
Classifier: Intended Audience :: Science/Research 
Classifier: Topic :: Scientific/Engineering :: Astronomy
Classifier: Programming Language :: Python :: 3
Classifier: License :: OSI Approved :: MIT License
License-File: LICENSE
Requires-Dist: numpy
Requires-Dist: scipy
Requires-Dist: astropy
Requires-Dist: matplotlib
